pyweblog/__init__.py
pyweblog/SDK_WS/__init__.py
pyweblog/SDK_WS/main.py
pythonweblog_client_ws-0.7.0.dist-info/METADATA
pythonweblog_client_ws-0.7.0.dist-info/WHEEL
pythonweblog_client_ws-0.7.0.dist-info/top_level.txt
pythonweblog_client_ws-0.7.0.dist-info/RECORD
