Metadata-Version: 2.4
Name: pythonweblog_client_ws
Version: 0.7.0
Summary: Python client for the pythonweblog
Home-page: https://github.com/asuma312/python-weblogging
Author: Lucas Bueno
Author-email: asuma312@gmail.com
Keywords: pythonweblog,python,client,websocket,logging,log,logger
Classifier: Programming Language :: Python :: 3
Classifier: License :: OSI Approved :: MIT License
Classifier: Operating System :: OS Independent
Requires-Python: >=3.9
Requires-Dist: python-socketio
Requires-Dist: websocket-client
Dynamic: author
Dynamic: author-email
Dynamic: classifier
Dynamic: description
Dynamic: description-content-type
Dynamic: home-page
Dynamic: keywords
Dynamic: requires-dist
Dynamic: requires-python
Dynamic: summary
